pyba/Camera.py
pyba/CameraNetwork.py
pyba/config.py
pyba/plot.py
pyba/pyba.py
pyba/util.py
pyba-0.13.dist-info/METADATA
pyba-0.13.dist-info/WHEEL
pyba-0.13.dist-info/top_level.txt
pyba-0.13.dist-info/RECORD
