Metadata-Version: 2.1
Name: pyba
Version: 0.13
Summary: Python Bundle Adjustment Routines
Home-page: https://github.com/semihgunel/PyBundleAdjustment
Author: Semih Günel
License: UNKNOWN
Platform: UNKNOWN
